ftmq/__init__.py
ftmq/aggregate.py
ftmq/aggregations.py
ftmq/cli.py
ftmq/enums.py
ftmq/filters.py
ftmq/io.py
ftmq/logging.py
ftmq/model/__init__.py
ftmq/model/dataset.py
ftmq/model/entity.py
ftmq/model/mixins.py
ftmq/model/stats.py
ftmq/query.py
ftmq/similar.py
ftmq/sql.py
ftmq/store/__init__.py
ftmq/store/aleph.py
ftmq/store/base.py
ftmq/store/fragments/__init__.py
ftmq/store/fragments/dataset.py
ftmq/store/fragments/loader.py
ftmq/store/fragments/settings.py
ftmq/store/fragments/store.py
ftmq/store/fragments/utils.py
ftmq/store/lake.py
ftmq/store/level.py
ftmq/store/memory.py
ftmq/store/redis.py
ftmq/store/sql.py
ftmq/types.py
ftmq/util.py
ftmq-4.3.4.dist-info/METADATA
ftmq-4.3.4.dist-info/WHEEL
ftmq-4.3.4.dist-info/entry_points.txt
ftmq-4.3.4.dist-info/licenses/LICENSE
ftmq-4.3.4.dist-info/licenses/NOTICE
ftmq-4.3.4.dist-info/RECORD
