Metadata-Version: 2.4
Name: ftmq
Version: 4.3.4
Summary: followthemoney query dsl and io helpers
License: AGPLv3+
License-File: LICENSE
License-File: NOTICE
Author: Simon Wörpel
Author-email: simon.woerpel@pm.me
Requires-Python: >=3.11,<4
Classifier: Intended Audience :: Developers
Classifier: Operating System :: OS Independent
Classifier: Programming Language :: Python
Classifier: Programming Language :: Python :: 3.11
Classifier: Programming Language :: Python :: 3.12
Classifier: Programming Language :: Python :: 3.13
Provides-Extra: aleph
Provides-Extra: lake
Provides-Extra: level
Provides-Extra: postgres
Provides-Extra: redis
Provides-Extra: sql
Requires-Dist: alephclient (>=2.6.0,<3.0.0) ; extra == "aleph"
Requires-Dist: anystore (>=0.4.2,<0.5.0)
Requires-Dist: click (>=8.2.1,<9.0.0)
Requires-Dist: click-default-group (>=1.2.4,<2.0.0)
Requires-Dist: deltalake (>=1.2.1,<2.0.0) ; extra == "lake"
Requires-Dist: duckdb (>=1.4.1,<2.0.0) ; extra == "lake"
Requires-Dist: fakeredis (>=2.26.2,<3.0.0) ; extra == "redis"
Requires-Dist: followthemoney (>=4.3.4,<5.0.0)
Requires-Dist: furl (>=2.1.4,<3.0.0) ; extra == "aleph"
Requires-Dist: nomenklatura (>=4.3.2,<5.0.0)
Requires-Dist: orjson (>=3.10.18,<4.0.0)
Requires-Dist: pandas (>=2.3.3,<3.0.0) ; extra == "lake"
Requires-Dist: plyvel (>=1.5.1,<2.0.0) ; extra == "level"
Requires-Dist: psycopg[pool] (>=3.2.9,<4.0.0) ; extra == "postgres"
Requires-Dist: pyarrow (>=21.0.0,<22.0.0) ; extra == "lake"
Requires-Dist: pydantic (>=2.11.3,<3.0.0)
Requires-Dist: pyicu (>=2.15.2,<3.0.0)
Requires-Dist: redis (>=5.2.1,<6.0.0) ; extra == "redis"
Requires-Dist: rigour (>=1.5.0,<2.0.0)
Requires-Dist: sqlalchemy (>=2.0.36,<3.0.0) ; extra == "postgres"
Requires-Dist: sqlalchemy (>=2.0.36,<3.0.0) ; extra == "sql"
Project-URL: Documentation, https://docs.investigraph.dev/lib/ftmq
Project-URL: Homepage, https://docs.investigraph.dev/lib/ftmq
Project-URL: Issues, https://github.com/dataresearchcenter/ftmq/issues
Project-URL: Repository, https://github.com/dataresearchcenter/ftmq
